[
  {
    "id":"9",
    "name": "Bic Pencils",
    "price": "5.36",
    "imageUrl":"images/Articulos/bicpencils.jpg"
  },

  {
    "id":"10",
    "name": "Bic Pens",
    "price": "4.58",
    "imageUrl":"images/Articulos/bicpen.jpg"
  },
  {
    "id":"11",
    "name": "Ti 36 Calculator",
    "price": "19.99",
    "imageUrl":"images/Articulos/ti36.jpg"
  },
  {
    "id":"12",
    "name": "JeanBook Notebook",
    "price": "1.95",
    "imageUrl":"images/Articulos/jeanbook.jpg"
  },
  {
    "id":"13",
    "name": "5 Star Notebook",
    "price": "2.99",
    "imageUrl":"images/Articulos/Notebook5star.jpg"
  }

]